phiona/__init__.py
phiona/core.py
phiona/tests.py
phiona-1.0.0.dist-info/licenses/LICENSE
phiona-1.0.0.dist-info/METADATA
phiona-1.0.0.dist-info/WHEEL
phiona-1.0.0.dist-info/top_level.txt
phiona-1.0.0.dist-info/RECORD
