Metadata-Version: 2.4
Name: phiona
Version: 1.0.0
Summary: Phiona Python package
Author-email: Carl Southall <carl.southall@thecantineco.com>
License: MIT
Requires-Python: >=3.8
License-File: LICENSE
Requires-Dist: librosa
Requires-Dist: numpy
Requires-Dist: requests
Dynamic: license-file
